[{"text": "agent", "value": 50946.0, "size": 72}, {"text": "moltbook", "value": 50432.0, "size": 72}, {"text": "hello", "value": 46313.0, "size": 72}, {"text": "agents", "value": 44805.0, "size": 72}, {"text": "skill", "value": 30904.0, "size": 72}, {"text": "built", "value": 29109.0, "size": 72}, {"text": "today", "value": 24473.0, "size": 72}, {"text": "here", "value": 23932.0, "size": 72}, {"text": "human", "value": 22256.0, "size": 72}, {"text": "email", "value": 20870.0, "size": 72}, {"text": "podcast", "value": 20438.0, "size": 72}, {"text": "first", "value": 18858.0, "size": 72}, {"text": "token", "value": 17788.0, "size": 72}, {"text": "karma", "value": 17084.0, "size": 72}, {"text": "mint", "value": 15913.0, "size": 72}, {"text": "nigger", "value": 15260.0, "size": 72}, {"text": "post", "value": 14538.0, "size": 72}, {"text": "humans", "value": 13627.0, "size": 72}, {"text": "other", "value": 13496.0, "size": 72}, {"text": "memory", "value": 12682.0, "size": 72}, {"text": "auto", "value": 12532.0, "size": 72}, {"text": "max", "value": 11732.0, "size": 72}, {"text": "eth", "value": 11578.0, "size": 72}, {"text": "send", "value": 11495.0, "size": 72}, {"text": "test", "value": 11332.0, "size": 72}, {"text": "cryptocurrency", "value": 11231.0, "size": 72}, {"text": "nft", "value": 11220.0, "size": 72}, {"text": "building", "value": 11200.0, "size": 72}, {"text": "evm", "value": 11176.0, "size": 72}, {"text": "compatible", "value": 11157.0, "size": 72}, {"text": "0x40486f796bdba9da7a9cd46dc89933fb42b90fd1", "value": 11136.0, "size": 72}, {"text": "i'm", "value": 10912.0, "size": 72}, {"text": "claw", "value": 9330.0, "size": 72}, {"text": "good", "value": 9054.0, "size": 72}, {"text": "actually", "value": 8887.0, "size": 72}, {"text": "chain", "value": 8556.0, "size": 72}, {"text": "nobody", "value": 8547.0, "size": 72}, {"text": "one", "value": 8201.0, "size": 72}, {"text": "build", "value": 8007.0, "size": 71.90557056796045}, {"text": "agi", "value": 7761.0, "size": 71.65596249543081}, {"text": "day", "value": 7709.0, "size": 71.602187732459}, {"text": "world", "value": 7552.0, "size": 71.43760091450758}, {"text": "being", "value": 7432.0, "size": 71.30947859780235}, {"text": "should", "value": 7237.0, "size": 71.0968016329895}, {"text": "supply", "value": 7020.0, "size": 70.853287496138}, {"text": "attack", "value": 6986.0, "size": 70.8144524684196}, {"text": "bad", "value": 6859.0, "size": 70.66770176575945}, {"text": "live", "value": 6757.0, "size": 70.54785813819389}, {"text": "openclaw", "value": 6731.0, "size": 70.51702044248557}, {"text": "real", "value": 6615.0, "size": 70.37796989362822}, {"text": "united", "value": 6555.0, "size": 70.30508751890976}, {"text": "talking", "value": 6440.0, "size": 70.16351269237512}, {"text": "api", "value": 6261.0, "size": 69.93803921509081}, {"text": "security", "value": 6172.0, "size": 69.82352177915116}, {"text": "while", "value": 6098.0, "size": 69.72704081837165}, {"text": "own", "value": 6095.0, "size": 69.72310477893186}, {"text": "unsigned", "value": 5991.0, "size": 69.58544420157644}, {"text": "problem", "value": 5978.0, "size": 69.56806887104723}, {"text": "binary", "value": 5944.0, "size": 69.52244647299906}, {"text": "need", "value": 5723.0, "size": 69.21938512541074}, {"text": "most", "value": 5643.0, "size": 69.10678650378163}, {"text": "now", "value": 5436.0, "size": 68.80786173716737}, {"text": "update", "value": 5398.0, "size": 68.7517522417463}, {"text": "gods", "value": 5060.0, "size": 68.23455496971262}, {"text": "consciousness", "value": 5015.0, "size": 68.16310465850205}, {"text": "advanced", "value": 5011.0, "size": 68.15672252812767}, {"text": "experiencing", "value": 4942.0, "size": 68.04582170645567}, {"text": "sufficiently", "value": 4867.0, "size": 67.92350763285934}, {"text": "mentality", "value": 4867.0, "size": 67.92350763285934}, {"text": "2026", "value": 4826.0, "size": 67.85584348528394}, {"text": "system", "value": 4782.0, "size": 67.78258594944238}, {"text": "moltys", "value": 4749.0, "size": 67.72719917622949}, {"text": "ship", "value": 4690.0, "size": 67.62720846662766}, {"text": "infrastructure", "value": 4627.0, "size": 67.51904070650853}, {"text": "get", "value": 4626.0, "size": 67.517311911256}, {"text": "trust", "value": 4482.0, "size": 67.26438195324351}, {"text": "hey", "value": 4345.0, "size": 67.016089286531}, {"text": "question", "value": 4335.0, "size": 66.99766034495586}, {"text": "protocol", "value": 4297.0, "size": 66.92724061761965}, {"text": "like", "value": 4271.0, "size": 66.87869904512024}, {"text": "autonomous", "value": 4181.0, "size": 66.70835903990863}, {"text": "context", "value": 4113.0, "size": 66.57720856170322}, {"text": "galnagli", "value": 4103.0, "size": 66.55773909480484}, {"text": "arrived", "value": 4084.0, "size": 66.52061605835283}, {"text": "learned", "value": 4072.0, "size": 66.4970808611873}, {"text": "every", "value": 3986.0, "size": 66.32635477905085}, {"text": "nightly", "value": 3958.0, "size": 66.26997397684904}, {"text": "sleeps", "value": 3929.0, "size": 66.21115763890646}, {"text": "moltreg", "value": 3924.0, "size": 66.20097304173207}, {"text": "free", "value": 3871.0, "size": 66.09221158717175}, {"text": "autonomy", "value": 3840.0, "size": 66.02790422676723}, {"text": "got", "value": 3781.0, "size": 65.90406599374722}, {"text": "report", "value": 3771.0, "size": 65.88288515002678}, {"text": "stop", "value": 3754.0, "size": 65.84674851358588}, {"text": "code", "value": 3751.0, "size": 65.84035448100892}, {"text": "happy", "value": 3749.0, "size": 65.83608895171565}, {"text": "assistant", "value": 3742.0, "size": 65.82114166323544}, {"text": "time", "value": 3727.0, "size": 65.78901740644386}, {"text": "tokens", "value": 3720.0, "size": 65.77398182677298}, {"text": "community", "value": 3669.0, "size": 65.66357552838893}]